toolmate/README.md
toolmate/__init__.py
toolmate/autoassist.py
toolmate/autobuilder.py
toolmate/autoretriever.py
toolmate/chatgpt.py
toolmate/check_on_android.txt
toolmate/codey.py
toolmate/commandprompt.py
toolmate/config.py
toolmate/eTextEdit.py
toolmate/geminipro.py
toolmate/geminiprovision.py
toolmate/groqchat.py
toolmate/llamacpp.py
toolmate/llamacppserver.py
toolmate/main.py
toolmate/mistralchat.py
toolmate/ollamachat.py
toolmate/package_name.txt
toolmate/palm2.py
toolmate/qt.py
toolmate/rag.py
toolmate/requirements.txt
toolmate/requirements_android.txt
toolmate/servers.py
toolmate/systemtray.py
toolmate/audio/notification1.mp3
toolmate/audio/notification1_mild.mp3
toolmate/audio/notification2.mp3
toolmate/audio/notification2_mild.mp3
toolmate/docs/Action Menu.md
toolmate/docs/Additional Chat Model.md
toolmate/docs/Android Versions.md
toolmate/docs/Beyond LetMeDoItAI.md
toolmate/docs/CLI Options.md
toolmate/docs/Change AI Backends and Models.md
toolmate/docs/Chat Record Management.md
toolmate/docs/Configure Ollama Server.md
toolmate/docs/Custom System Messages.md
toolmate/docs/Customise Assistant Name.md
toolmate/docs/Docker Setup on Android Termux.md
toolmate/docs/Download LLM in GGUF Format.md
toolmate/docs/Edit Config Manually.md
toolmate/docs/Edit Current Conversation.md
toolmate/docs/Examples.md
toolmate/docs/Fabric Integration.md
toolmate/docs/First launch.md
toolmate/docs/Function Call Approach with Any LLMs.md
toolmate/docs/GPU Acceleration with Llama_cpp server.md
toolmate/docs/GPU Acceleration.md
toolmate/docs/Google Cloud Service Credential Setup.md
toolmate/docs/Groq API Setup.md
toolmate/docs/Install Python.md
toolmate/docs/Install ToolMate.md
toolmate/docs/Install ffmpeg.md
toolmate/docs/LetMeDoIt Mode.md
toolmate/docs/Miscellaneous.md
toolmate/docs/Mistral API Setup.md
toolmate/docs/Offline TTS - Linux.md
toolmate/docs/Offline TTS - Windows.md
toolmate/docs/Offline TTS - macOS.md
toolmate/docs/OpenAI API Setup.md
toolmate_android-0.5.8.dist-info/METADATA
toolmate_android-0.5.8.dist-info/WHEEL
toolmate_android-0.5.8.dist-info/entry_points.txt
toolmate_android-0.5.8.dist-info/top_level.txt
toolmate_android-0.5.8.dist-info/RECORD
