Metadata-Version: 2.1
Name: toolmate_android
Version: 0.5.8
Summary: ToolMate AI, developed by Eliran Wong, is a cutting-edge AI companion that seamlessly integrates agents, tools, and plugins to excel in conversations, generative work, and task execution. Supports custom workflow and plugins to automate multi-step actions.
Home-page: https://letmedoit.ai
Author: Eliran Wong
Author-email: support@letmedoit.ai
License: GNU General Public License (GPL)
Project-URL: Source, https://github.com/eliranwong/toolmate
Project-URL: Tracker, https://github.com/eliranwong/toolmate/issues
Project-URL: Documentation, https://github.com/eliranwong/toolmate/wiki
Project-URL: Funding, https://www.paypal.me/letmedoitai
Keywords: ai assistant ollama llama llamacpp groq openai chatgpt gemini autogen rag agent stable-diffusion fabric dalle imagen
Classifier: Development Status :: 5 - Production/Stable
Classifier: Intended Audience :: End Users/Desktop
Classifier: Topic :: Utilities
Classifier: Topic :: Scientific/Engineering :: Artificial Intelligence
Classifier: Topic :: Software Development :: Build Tools
Classifier: License :: OSI Approved :: GNU General Public License v3 or later (GPLv3+)
Classifier: Programming Language :: Python :: 3.8
Classifier: Programming Language :: Python :: 3.9
Classifier: Programming Language :: Python :: 3.10
Classifier: Programming Language :: Python :: 3.11
Classifier: Programming Language :: Python :: 3.12
Requires-Python: >=3.8, <3.13
Requires-Dist: wheel
Requires-Dist: setuptools
Requires-Dist: pipdeptree
Requires-Dist: mistralai>=1.2.0
Requires-Dist: sqlmodel==0.0.22
Requires-Dist: tabulate==0.9.0
Requires-Dist: termcolor==2.4.0
Requires-Dist: wcwidth==0.2.13
Requires-Dist: wikipedia==1.4.0
Requires-Dist: aiosignal==1.3.1
Requires-Dist: xlrd==2.0.1
Requires-Dist: aiohappyeyeballs==2.4.0
Requires-Dist: xyzservices==2024.9.0
Requires-Dist: zope.interface==7.0.3
Requires-Dist: annotated-types==0.7.0
Requires-Dist: exceptiongroup==1.2.2
Requires-Dist: blinker==1.8.2
Requires-Dist: h11==0.14.0
Requires-Dist: cachetools==5.5.0
Requires-Dist: deepdiff==8.0.1
Requires-Dist: marshmallow==3.22.0
Requires-Dist: httplib2==0.22.0
Requires-Dist: frozenlist==1.4.1
Requires-Dist: googlesearch-python
Requires-Dist: itsdangerous==2.2.0
Requires-Dist: imageio==2.35.1
Requires-Dist: humanfriendly==10.0
Requires-Dist: httptools==0.6.1
Requires-Dist: joblib==1.4.2
Requires-Dist: multitasking==0.0.11
Requires-Dist: jedi==0.19.1
Requires-Dist: kiwisolver==1.4.7
Requires-Dist: lazy-loader==0.4
Requires-Dist: protobuf==4.25.3
Requires-Dist: ollama==0.3.3
Requires-Dist: groq==0.11.0
Requires-Dist: openai==1.52.2
Requires-Dist: tiktoken==0.8.0
Requires-Dist: soundfile==0.12.1
Requires-Dist: sounddevice==0.5.0
Requires-Dist: elevenlabs==1.5.0
Requires-Dist: huggingface-hub==0.26.1
Requires-Dist: langchain-core==0.3.12
Requires-Dist: langchain==0.3.4
Requires-Dist: langchain-community==0.3.3
Requires-Dist: langchain-openai==0.2.3
Requires-Dist: langchain-ollama==0.2.0
Requires-Dist: langchain-text-splitters==0.3.0
Requires-Dist: requests
Requires-Dist: argparse
Requires-Dist: folium
Requires-Dist: sympy
Requires-Dist: prompt-toolkit
Requires-Dist: Pygments
Requires-Dist: datetime
Requires-Dist: geocoder
Requires-Dist: art
Requires-Dist: gTTS
Requires-Dist: yt-dlp
Requires-Dist: qrcode
Requires-Dist: pyperclip
Requires-Dist: colorama
Requires-Dist: pillow
Requires-Dist: einops
Requires-Dist: python-magic
Requires-Dist: feedparser
Requires-Dist: html2text
Requires-Dist: pypdf
Requires-Dist: setuptools-rust
Requires-Dist: SpeechRecognition
Requires-Dist: pydub
Requires-Dist: pytz
Requires-Dist: geopy
Requires-Dist: psutil
Requires-Dist: flashtext
Requires-Dist: wikipedia
Requires-Dist: tqdm
Requires-Dist: edge-tts
Requires-Dist: ftfy
Provides-Extra: bible
Requires-Dist: uniquebible>=0.1.99; extra == "bible"
